pyblish_3dsmax/__init__.py
pyblish_3dsmax/app.py
pyblish_3dsmax/version.py
pyblish_3dsmax/plugins/__init__.py
pyblish_3dsmax/plugins/collect_current_file.py
pyblish_3dsmax-0.1.0.dist-info/LICENSE
pyblish_3dsmax-0.1.0.dist-info/METADATA
pyblish_3dsmax-0.1.0.dist-info/WHEEL
pyblish_3dsmax-0.1.0.dist-info/top_level.txt
pyblish_3dsmax-0.1.0.dist-info/RECORD
