Metadata-Version: 2.1
Name: pyblish-3dsmax
Version: 0.1.0
Summary: Pyblish for 3ds Max.
Home-page: https://github.com/pyblish/pyblish-3dsmax
Author: Pyblish contributors
Author-email: me@mottosso.com
License: LGPL
Platform: UNKNOWN
Classifier: Development Status :: 4 - Beta
Classifier: Intended Audience :: Developers
Classifier: License :: OSI Approved :: GNU Lesser General Public License v3 (LGPLv3)
Classifier: Programming Language :: Python :: 2
Classifier: Programming Language :: Python :: 3
Classifier: Programming Language :: Python :: 3.5
Classifier: Programming Language :: Python :: 3.6
Classifier: Programming Language :: Python :: 3.7
Classifier: Programming Language :: Python :: 3.8
Classifier: Topic :: Software Development :: Libraries :: Python Modules
Requires-Dist: qt.py (>=1.3)
Requires-Dist: pyblish-base (>=1.2.1)
Requires-Dist: pyblish-lite (>=0.8.0)
